Workbook
Name Master1: #REF!
Name MasterTAble: Master!$A$1:$K$187

Sheet Master
A1: Фирма | C1: СТАТУС | D1: MAND | E1: Счетоводител | F1: Заместване | G1: ТРЗ | H1: ХОНОРАР | I1: ТРЗ Отг. | J1: ТРЗ Статус | K1: Данък изт./СИДО
A2: 2Б ООД | C2: АКТИВНА | D2: NULA | E2: АНУШКА РАДЕВА | F2: ВИОЛИНА МИТАКСОВА | G2: АТАНАСКА ГОСПОДИНОВА | H2: 0 | I2: АТАНАСКА ГОСПОДИНОВА | J2: СОЛ | K2: НЕ
A3: АВОМИС ЕООД | B3: Ок | C3: АКТИВНА | D3: NULA | E3: АНУШКА РАДЕВА | F3: КРАСИМИРА ГЕОРГИЕВА | H3: 0 | I3: АТАНАСКА ГОСПОДИНОВА | J3: ДУК | Q3: =PayRoll!A2 -> АНГЕЛ ТОДОРОВ | R3: =PayRoll!H2 -> 1413.2 | S3: =SUMIF(E:E,Q3,H:H) -> 200
A4: АГРИ СТРОЙ ЕООД | B4: Ок | C4: АКТИВНА | D4: 257 | E4: МАЯ МАТАНСКА | F4: ВИОЛИНА МИТАКСОВА | H4: 0 | Q4: =PayRoll!A3 -> АНЕЛИЯ ПЕНКОВА | R4: =PayRoll!H3 -> 1413.2 | S4: =SUMIF(E:E,Q4,H:H) -> 0
A5: АГРОГРУП 2017 ООД | B5: Ок | C5: АКТИВНА | D5: NULA | F5: ВИОЛИНА МИТАКСОВА | H5: 150 | M5: Ок | Q5: =PayRoll!A4 -> АНЕЛИЯ ЩЕРЕВА | R5: =PayRoll!H4 -> 0 | S5: =SUMIF(E:E,Q5,H:H) -> 0
A6: АГРОДЕН ООД | B6: Ок | C6: АКТИВНА | D6: 358 | F6: КРАСИМИРА ГЕОРГИЕВА | H6: 700 | I6: СИЛВИЯ ИВАНОВА | J6: СОЛ+ | M6: Проблемен | Q6: =PayRoll!A5 -> АТАНАСКА ГОСПОДИНОВА | R6: =PayRoll!H5 -> 1613.2 | S6: =SUMIF(E:E,Q6,H:H) -> 0
A7: АДВАНС ХОУМС ООД | B7: Ок | C7: АКТИВНА | D7: NULA | F7: РАДКА НИКОЛОВА | H7: 250 | I7: АТАНАСКА ГОСПОДИНОВА | J7: А1 | M7: Изискващ | Q7: =PayRoll!A6 -> АНУШКА РАДЕВА | R7: =PayRoll!H6 -> 1200 | S7: =SUMIF(E:E,Q7,H:H) -> 3180
A8: АДВОКАТСКО СЪДРУЖИЕ ЗЛАТКОВА И БРЕЗОВСКА | B8: Ок | C8: АКТИВНА | D8: 465 | E8: ПЕТЯ ПАВЛОВА | F8: РАДКА НИКОЛОВА | H8: 250 | I8: АТАНАСКА ГОСПОДИНОВА | J8: СОЛ | M8: Обемен | Q8: =PayRoll!A7 -> ВИОЛИНА МИТАКСОВА | R8: =PayRoll!H7 -> 1693.2 | S8: =SUMIF(E:E,Q8,H:H) -> 0
A9: АДРИАТИКА БЛУ ЕООД | B9: Ок | C9: АКТИВНА | D9: NULA | E9: ПЕТЯ ПАВЛОВА | F9: ВИОЛИНА МИТАКСОВА | H9: 800 | I9: СИЛВИЯ ИВАНОВА | J9: ДУК+ | Q9: =PayRoll!A8 -> ГАЛИНА ГЕОРГИЕВА | R9: =PayRoll!H8 -> 1363.2 | S9: =SUMIF(E:E,Q9,H:H) -> 7250
A10: АКВА КРАФТ ЕООД | C10: НУЛЕВО | D10: 281 | E10: АНУШКА РАДЕВА | F10: РАДКА НИКОЛОВА | H10: 0 | Q10: =PayRoll!A9 -> ДИМИТРИНА КОЛЕВА | R10: =PayRoll!H9 -> 1588.2 | S10: =SUMIF(E:E,Q10,H:H) -> 0
A11: АЛЕКС К 2002 ЕООД | B11: Изискващ | C11: АКТИВНА | D11: NULA | E11: ГАЛИНА ГЕОРГИЕВА | F11: КРАСИМИРА ГЕОРГИЕВА | H11: 1100 | I11: АТАНАСКА ГОСПОДИНОВА | J11: ДУК+ | Q11: =PayRoll!A10 -> КРАСИМИРА ГЕОРГИЕВА | R11: =PayRoll!H10 -> 1693.2 | S11: =SUMIF(E:E,Q11,H:H) -> 0
A12: ВЕК ТРЕЙДИНГ ООД | B12: Проблемен | C12: АКТИВНА | D12: 010 | E12: МАЯ МАТАНСКА | F12: ВИОЛИНА МИТАКСОВА | H12: 700 | I12: АТАНАСКА ГОСПОДИНОВА | J12: СОЛ+ | Q12: =PayRoll!A11 -> МАРИЯ МОНЧЕВСКА | R12: =PayRoll!H11 -> 1663.2 | S12: =SUMIF(E:E,Q12,H:H) -> 0
A13: АЛИСА 34 ЕООД | C13: НУЛЕВО | D13: 296 | E13: АНУШКА РАДЕВА | F13: РАДКА НИКОЛОВА | H13: 0 | Q13: =PayRoll!A12 -> МАЯ МАТАНСКА | R13: =PayRoll!H12 -> 1200 | S13: =SUMIF(E:E,Q13,H:H) -> 4300
A14: АЛФА БЕТА БИЛД ООД | E14: АНГЕЛ ТОДОРОВ | H14: 200 | Q14: =PayRoll!A13 -> ПЕТЯ ПАВЛОВА | R14: =PayRoll!H13 -> 1463.2 | S14: =SUMIF(E:E,Q14,H:H) -> 0
A15: ГРИЙН ХОУМС ЕООД | B15: Проблемен | C15: НУЛЕВО | E15: АНУШКА РАДЕВА | F15: КРАСИМИРА ГЕОРГИЕВА | H15: 0 | Q15: =PayRoll!A14 -> РАДКА НИКОЛОВА | R15: =PayRoll!H14 -> 2350.6916 | S15: =SUMIF(E:E,Q15,H:H) -> 1700
A16: КОНСТРУКТ СТРОЙ ООД | B16: Проблемен | C16: НУЛЕВО | D16: 241 | E16: АНУШКА РАДЕВА | F16: РАДКА НИКОЛОВА | H16: 0 | Q16: =PayRoll!A15 -> СИЛВИЯ СТОЯНЧЕВА | R16: =PayRoll!H15 -> 1513.2 | S16: =SUMIF(E:E,Q16,H:H) -> 0
A17: ПЕРЛАИНВЕСТ ООД | B17: Изискващ | C17: АКТИВНА | D17: NULA | F17: КРАСИМИРА ГЕОРГИЕВА | H17: 1600 | I17: АТАНАСКА ГОСПОДИНОВА | J17: ДУК+ | Q17: =PayRoll!A16 -> СИЛВИЯ ИВАНОВА | R17: =PayRoll!H16 -> 1463.2 | S17: =SUMIF(E:E,Q17,H:H) -> 0
A18: ПЛАМА СОФТ ООД | B18: Изискващ | C18: АКТИВНА | D18: NULA | F18: ВИОЛИНА МИТАКСОВА | H18: 880 | I18: АТАНАСКА ГОСПОДИНОВА | J18: СОЛ+ | R18: =SUM(R3:R17) -> 21630.892
A19: АРИМА КОНСУЛТ ООД | C19: НУЛЕВО | D19: 438 | E19: АНУШКА РАДЕВА | F19: РАДКА НИКОЛОВА | H19: 0
A20: АРТИСЕТ ООД | C20: НУЛЕВО | D20: 400 | E20: АНУШКА РАДЕВА | F20: РАДКА НИКОЛОВА | H20: 0
A21: АСЕТ ИНВЕСТМЪНТ ЕООД | C21: НУЛЕВО | E21: АНУШКА РАДЕВА | F21: КРАСИМИРА ГЕОРГИЕВА | H21: 0
A22: АСЕТ ФАРМА ЕООД | C22: НУЛЕВО | E22: АНУШКА РАДЕВА | F22: КРАСИМИРА ГЕОРГИЕВА | H22: 0
A23: АСИ 75 | C23: НУЛЕВО | D23: 172 | E23: АНУШКА РАДЕВА | F23: РАДКА НИКОЛОВА | H23: 0
A24: БОНАФАЙД ЕООД | C24: НУЛЕВО | D24: 425 | E24: АНУШКА РАДЕВА | F24: РАДКА НИКОЛОВА | H24: 0
A25: БОРЕ ГРУП ЕООД | B25: Обемен | C25: АКТИВНА | D25: 468 | F25: КРАСИМИРА ГЕОРГИЕВА | H25: 1500 | I25: АТАНАСКА ГОСПОДИНОВА | J25: ДУК+
A26: БРАТЯ ДИМОВИ 2009 ООД | B26: Ок | C26: АКТИВНА | D26: NULA | E26: АНУШКА РАДЕВА | F26: ВИОЛИНА МИТАКСОВА | H26: 400 | I26: АТАНАСКА ГОСПОДИНОВА | J26: СОЛ
A27: ВАИС ГРУП 77 ЕООД | B27: Ок | C27: АКТИВНА | D27: NULA | E27: ГАЛИНА ГЕОРГИЕВА | F27: КРАСИМИРА ГЕОРГИЕВА | H27: 0
A28: ВАЛСПОРТ 84 ЕООД | B28: Ок | C28: АКТИВНА | D28: NULA | E28: АНУШКА РАДЕВА | F28: КРАСИМИРА ГЕОРГИЕВА | H28: 200 | I28: АТАНАСКА ГОСПОДИНОВА | J28: СОЛ+
A29: ВАТЕРПОЛО КОМЕРС ЕООД | B29: Ок | C29: АКТИВНА | D29: NULA | F29: ВИОЛИНА МИТАКСОВА | H29: 100
A30: ПРЕКОС ООД | B30: Изискващ | C30: АКТИВНА | D30: 036 | F30: ВИОЛИНА МИТАКСОВА | H30: 850 | I30: АТАНАСКА ГОСПОДИНОВА | J30: ДУК+
A31: ВЕКО СТРОЙ 2009 ЕООД | C31: АКТИВНА | D31: 085 | E31: МАЯ МАТАНСКА | F31: ВИОЛИНА МИТАКСОВА | H31: 0 | I31: АТАНАСКА ГОСПОДИНОВА | J31: СОЛ
A32: ВИКИ 2 ООД | B32: Ок | C32: АКТИВНА | D32: NULA | E32: АНУШКА РАДЕВА | F32: ВИОЛИНА МИТАКСОВА | H32: 300 | I32: АТАНАСКА ГОСПОДИНОВА | J32: СОЛ+
A33: ВИКИВАТ ООД | B33: Обемен | C33: АКТИВНА | D33: 467 | E33: МАЯ МАТАНСКА | F33: КРАСИМИРА ГЕОРГИЕВА | H33: 800 | I33: СИЛВИЯ ИВАНОВА | J33: СОЛ+
A34: ВИЛХЕЛМ БЪЛГАРИЯ ЕООД | B34: Ок | C34: АКТИВНА | D34: NULA | F34: КРАСИМИРА ГЕОРГИЕВА | H34: 210 | I34: АТАНАСКА ГОСПОДИНОВА | J34: Служители
A35: РЕТУР 07 ЕООД | B35: Проблемен | C35: АКТИВНА | D35: 056 | F35: ВИОЛИНА МИТАКСОВА | H35: 500 | I35: АТАНАСКА ГОСПОДИНОВА | J35: ДУК+
A36: ВОМИС КОНСУЛТ ООД | B36: Ок | C36: АКТИВНА | D36: NULA | E36: АНУШКА РАДЕВА | F36: КРАСИМИРА ГЕОРГИЕВА | H36: 0 | I36: АТАНАСКА ГОСПОДИНОВА | J36: СОЛ+
A37: ГЕЗЕДЖИ ООД | C37: НУЛЕВО | D37: 451 | E37: АНУШКА РАДЕВА | F37: РАДКА НИКОЛОВА | H37: 0
A38: ГЕРИ МУР 2016 ЕООД | B38: Обемен | C38: АКТИВНА | D38: 277 | F38: КРАСИМИРА ГЕОРГИЕВА | H38: 1000 | I38: АТАНАСКА ГОСПОДИНОВА | J38: СОЛ+
A39: ГЛИТ ЦРО ЕООД | B39: Ок | C39: АКТИВНА | D39: NULA | E39: ДИМИТРИНА КОЛЕВА | F39: ВИОЛИНА МИТАКСОВА | H39: 500 | I39: АТАНАСКА ГОСПОДИНОВА | J39: ДУК
A40: ГРАФИС ООД | B40: Ок | C40: АКТИВНА | D40: NULA | E40: АНУШКА РАДЕВА | F40: ВИОЛИНА МИТАКСОВА | H40: 200 | I40: АТАНАСКА ГОСПОДИНОВА | J40: ДУК
A41: РОЯЛ ВИЖЪН ЕООД | B41: Проблемен | C41: БЕЗ ДЕЙНОСТ | E41: РАДКА НИКОЛОВА | F41: РАДКА НИКОЛОВА | H41: 0 | I41: АТАНАСКА ГОСПОДИНОВА | J41: ДУК+
A42: ДАРЛИН БЮТИ ЕООД | B42: Ок | C42: НУЛЕВО | D42: 405 | E42: АНУШКА РАДЕВА | F42: РАДКА НИКОЛОВА | H42: 0
A43: ДЕЙВИД ПИЕР БЮНЕТ | B43: Ок | C43: АКТИВНА | D43: NULA | E43: ДИМИТРИНА КОЛЕВА | F43: РАДКА НИКОЛОВА | H43: 200 | I43: АТАНАСКА ГОСПОДИНОВА | J43: СОЛ
A44: ГИМЕС ООД | B44: Ок | C44: АКТИВНА | D44: NULA | E44: АНУШКА РАДЕВА | F44: ВИОЛИНА МИТАКСОВА | H44: 0 | I44: АТАНАСКА ГОСПОДИНОВА | J44: СОЛ
A45: ДЕЙВИД ПОСТАЛ МАРКЕТ ООД | B45: Ок | C45: АКТИВНА | D45: 403 | F45: ВИОЛИНА МИТАКСОВА | H45: 200 | I45: АТАНАСКА ГОСПОДИНОВА | J45: ДУК+
A46: ДЕЙВИД ПРОФЕШЪНЪЛ ООД | B46: Ок | C46: АКТИВНА | D46: 411 | F46: ВИОЛИНА МИТАКСОВА | H46: 300 | I46: АТАНАСКА ГОСПОДИНОВА | J46: ДУК+
A47: ДЖИ ТИ ДРАЙВ ЕООД | B47: Ок | C47: АКТИВНА | D47: NULA | E47: АНУШКА РАДЕВА | F47: ВИОЛИНА МИТАКСОВА | H47: 100
A48: ДИВЕРСО ГРУП 13 ООД | B48: Ок | C48: АКТИВНА | D48: NULA | E48: ГАЛИНА ГЕОРГИЕВА | F48: ВИОЛИНА МИТАКСОВА | H48: 350 | I48: АТАНАСКА ГОСПОДИНОВА | J48: ДУК+
A49: СТ ПРОПЪРТИС ЕООД | B49: Изискващ | C49: АКТИВНА | D49: NULA | E49: ГАЛИНА ГЕОРГИЕВА | F49: КРАСИМИРА ГЕОРГИЕВА | H49: 300 | I49: АТАНАСКА ГОСПОДИНОВА
A50: ФРЕА 28 ЕООД | B50: Изискващ | C50: АКТИВНА | D50: 344 | F50: ВИОЛИНА МИТАКСОВА | H50: 200 | I50: СИЛВИЯ ИВАНОВА | J50: ДУК+
A51: ДИОНИС 13 ЕООД | C51: НУЛЕВО | D51: 202 | E51: АНУШКА РАДЕВА | F51: РАДКА НИКОЛОВА | H51: 0
A52: ХЕМИНГУЕЙ БЪЛГАРИЯ ЕООД | B52: Изискващ | C52: АКТИВНА | D52: NULA | E52: ГАЛИНА ГЕОРГИЕВА | F52: ВИОЛИНА МИТАКСОВА | H52: 1700 | I52: АТАНАСКА ГОСПОДИНОВА | J52: СОЛ+
A53: ДРАЙВ ХЪБ ЕООД | B53: Ок | C53: АКТИВНА | D53: NULA | E53: РАДКА НИКОЛОВА | F53: РАДКА НИКОЛОВА | H53: 0 | I53: АТАНАСКА ГОСПОДИНОВА | J53: СОЛ
A54: Дуайен Юръп-Производство на строителни химикали ЕООД | B54: Ок | C54: НУЛЕВО | E54: АНУШКА РАДЕВА | F54: РАДКА НИКОЛОВА | H54: 0
A55: ЕВРОТЕХ БЪЛГАРИЯ 2022 ЕООД | B55: Ок | C55: АКТИВНА | D55: NULA | F55: КРАСИМИРА ГЕОРГИЕВА | H55: 100 | I55: АТАНАСКА ГОСПОДИНОВА | J55: Служители
A56: ЕКОТЕРМ БЪЛГАРИЯ ЕООД | B56: Ок | C56: АКТИВНА | D56: NULA | E56: МАЯ МАТАНСКА | F56: КРАСИМИРА ГЕОРГИЕВА | H56: 200
A57: ЕЛ БЪЛГАРИЯ ЕООД | B57: Обемен | C57: АКТИВНА | D57: 290 | E57: МАЯ МАТАНСКА | F57: ВИОЛИНА МИТАКСОВА | H57: 1000 | I57: СИЛВИЯ ИВАНОВА | J57: ДУК+
A58: ЕЛИНМАР ООД | C58: БЕЗ ДДС | D58: NULA | F58: РАДКА НИКОЛОВА | H58: 0 | I58: АТАНАСКА ГОСПОДИНОВА | J58: СОЛ
A59: ЕСиЕМ ИНТЕРИО | C59: НУЛЕВО | D59: 470 | E59: АНУШКА РАДЕВА | F59: РАДКА НИКОЛОВА | H59: 0
A60: ЕН ТИ ДЖИ ГРУП 19 ЕДПК | C60: НУЛЕВО | D60: NULA | E60: АНУШКА РАДЕВА | F60: РАДКА НИКОЛОВА | H60: 0
A61: ЕРДЖИ 2000 ЕООД | C61: БЕЗ ДДС | E61: АНУШКА РАДЕВА | F61: ВИОЛИНА МИТАКСОВА | H61: 0 | I61: АТАНАСКА ГОСПОДИНОВА | J61: СОЛ+
A62: ЕС ФОР БИ ООД | B62: Ок | C62: АКТИВНА | D62: 381 | E62: ПЕТЯ ПАВЛОВА | F62: КРАСИМИРА ГЕОРГИЕВА | H62: 0
A63: ЕТ ВИКИВАТ | C63: БЕЗ ДДС | E63: РАДКА НИКОЛОВА | F63: КРАСИМИРА ГЕОРГИЕВА | H63: 0
A64: ЖИЗАТЕКС ООД | B64: Ок | C64: АКТИВНА | D64: NULA | F64: ВИОЛИНА МИТАКСОВА | H64: 0
A65: ЗВЕЗДА 21 ЕООД | B65: Ок | C65: АКТИВНА | D65: NULA | E65: ГАЛИНА ГЕОРГИЕВА | F65: ВИОЛИНА МИТАКСОВА | H65: 200
A66: ЗДРАВЧЕВИ ТРАНС ООД | C66: АКТИВНА | D66: 055 | E66: АНУШКА РАДЕВА | F66: ВИОЛИНА МИТАКСОВА | H66: 0 | I66: АТАНАСКА ГОСПОДИНОВА | J66: СОЛ+
A67: ЗЕМЕДЕЛСКО СТОПАНСТВО ПЕРУЩИЦА ЕООД | B67: Ок | C67: АКТИВНА | D67: 242 | E67: МАЯ МАТАНСКА | F67: ВИОЛИНА МИТАКСОВА | H67: 0 | I67: АТАНАСКА ГОСПОДИНОВА | J67: Служители
A68: ЗП ВЕЛИ КАРАХОДЖЕВ | B68: Ок | C68: БЕЗ ДДС | E68: МАЯ МАТАНСКА | F68: ВИОЛИНА МИТАКСОВА | H68: 0
A69: ИВС ИНВЕСТ ООД | B69: Ок | C69: БЕЗ ДДС | D69: NULA | E69: РАДКА НИКОЛОВА | F69: КРАСИМИРА ГЕОРГИЕВА | H69: 0 | I69: АТАНАСКА ГОСПОДИНОВА | J69: СОЛ
A70: ИМЕРИС МИНЕРАЛС БЪЛГАРИЯ АД | B70: Ок | C70: АКТИВНА | D70: SAP | E70: РАДКА НИКОЛОВА | F70: РАДКА НИКОЛОВА | H70: 1700
A71: ИНВЕНИО БЪЛГАРИЯ ЕООД | B71: Ок | C71: АКТИВНА | D71: NULA | E71: ПЕТЯ ПАВЛОВА | F71: КРАСИМИРА ГЕОРГИЕВА | H71: 250 | I71: СИЛВИЯ ИВАНОВА | J71: Служители
A72: ИНВЕНИО РК ЕООД | B72: Ок | C72: АКТИВНА | D72: NULA | E72: ПЕТЯ ПАВЛОВА | F72: КРАСИМИРА ГЕОРГИЕВА | H72: 2000 | I72: СИЛВИЯ ИВАНОВА | J72: Служители
A73: ИНВЕСТ ЛУКС ПРОПЪРТИ ЕООД | C73: НУЛЕВО | E73: АНУШКА РАДЕВА | F73: КРАСИМИРА ГЕОРГИЕВА | H73: 0
A74: ИСИ ПЛОВДИВ ЕООД | B74: Ок | C74: АКТИВНА | D74: NULA | E74: ГАЛИНА ГЕОРГИЕВА | F74: ВИОЛИНА МИТАКСОВА | H74: 200 | I74: АТАНАСКА ГОСПОДИНОВА | J74: Служители
A75: ИСИ ПЛОВДИВ ЕООД - одиторски файл | C75: АКТИВНА | E75: ВИОЛИНА МИТАКСОВА | F75: ВИОЛИНА МИТАКСОВА | H75: 0
A76: КАЛМАНОЛА ЕООД | B76: Ок | C76: АКТИВНА | D76: 471 | E76: ДИМИТРИНА КОЛЕВА | F76: РАДКА НИКОЛОВА | H76: 1000 | I76: АТАНАСКА ГОСПОДИНОВА | J76: СОЛ
A77: АЛЕКС С 2002 ЕООД | B77: Изискващ | C77: АКТИВНА | D77: NULA | E77: ГАЛИНА ГЕОРГИЕВА | F77: КРАСИМИРА ГЕОРГИЕВА | H77: 600 | I77: СИЛВИЯ ИВАНОВА | J77: ДУК+
A78: АНВЕРС КОМЕРС ЕООД | B78: Проблемен | C78: АКТИВНА | D78: 430 | E78: ПЕТЯ ПАВЛОВА | F78: РАДКА НИКОЛОВА | H78: 0
A79: КАРБУ ЕООД | B79: Ок | C79: АКТИВНА | D79: NULA | E79: АНУШКА РАДЕВА | F79: РАДКА НИКОЛОВА | H79: 100 | I79: АТАНАСКА ГОСПОДИНОВА | J79: СОЛ
A80: КИАРА НОВЕ ЕООД | C80: АКТИВНА | D80: NULA | E80: КРАСИМИРА ГЕОРГИЕВА | F80: КРАСИМИРА ГЕОРГИЕВА | H80: 500
A81: КИАРА ПРИВЕ ЕООД | C81: АКТИВНА | D81: NULA | E81: КРАСИМИРА ГЕОРГИЕВА | F81: КРАСИМИРА ГЕОРГИЕВА | H81: 0
A82: КИАРА - ФАРМ ЕООД | C82: НУЛЕВО | E82: АНУШКА РАДЕВА | F82: КРАСИМИРА ГЕОРГИЕВА | H82: 0
A83: КЛЪСТЪРМАРКЕТ БЪЛГАРИЯ ЕООД | B83: Ок | C83: АКТИВНА | D83: NULA | E83: ДИМИТРИНА КОЛЕВА | F83: КРАСИМИРА ГЕОРГИЕВА | H83: 520 | I83: АТАНАСКА ГОСПОДИНОВА | J83: Служители
A84: КМД ИМОТИ ЕООД | B84: Ок | C84: АКТИВНА | D84: NULA | E84: РАДКА НИКОЛОВА | F84: РАДКА НИКОЛОВА | H84: 0
A85: АНВЕРС КОМЕРСИАЛ ЕООД | B85: Проблемен | C85: АКТИВНА | D85: 429 | E85: ПЕТЯ ПАВЛОВА | F85: РАДКА НИКОЛОВА | H85: 0
A86: АНВЕРС КОНСТРУКТ ЕООД | B86: Проблемен | C86: АКТИВНА | D86: 428 | E86: ПЕТЯ ПАВЛОВА | F86: РАДКА НИКОЛОВА | H86: 600 | I86: СИЛВИЯ ИВАНОВА | J86: ДУК+
A87: КОНСУЛТ ПЛЮС ЕООД | B87: Ок | C87: АКТИВНА | D87: NULA | E87: РАДКА НИКОЛОВА | F87: РАДКА НИКОЛОВА | H87: 0 | I87: АТАНАСКА ГОСПОДИНОВА
A88: КОРЕКТ ИВ ЕООД | B88: Ок | C88: АКТИВНА | D88: NULA | E88: АНУШКА РАДЕВА | F88: ВИОЛИНА МИТАКСОВА | H88: 200 | I88: АТАНАСКА ГОСПОДИНОВА | J88: СОЛ
A89: КРЮ РЕПУБЛИК ЕООД | C89: НУЛЕВО | D89: NULA | E89: АНУШКА РАДЕВА | F89: РАДКА НИКОЛОВА | H89: 0
A90: КТК-КЪМПЛИТ ТРЕЙДИНГ КЪМПАНИ ЕООД | B90: Ок | C90: АКТИВНА | D90: NULA | E90: ДИМИТРИНА КОЛЕВА | F90: КРАСИМИРА ГЕОРГИЕВА | H90: 1500 | I90: АТАНАСКА ГОСПОДИНОВА | J90: ДУК
A91: КЮ ЕС ДЖИ ЕООД | B91: Ок | C91: АКТИВНА | D91: 426 | E91: ПЕТЯ ПАВЛОВА | F91: КРАСИМИРА ГЕОРГИЕВА | H91: 0 | I91: АТАНАСКА ГОСПОДИНОВА | J91: ДУК
A92: ЛБГ ЕООД | B92: Ок | C92: АКТИВНА | D92: 319 | E92: МАЯ МАТАНСКА | F92: ВИОЛИНА МИТАКСОВА | H92: 200
A93: ЛТИ ИНЖЕНЕРИНГ ЕООД | B93: Ок | C93: АКТИВНА | D93: NULA | E93: ГАЛИНА ГЕОРГИЕВА | F93: ВИОЛИНА МИТАКСОВА | H93: 1000 | I93: АТАНАСКА ГОСПОДИНОВА | J93: ДУК+
A94: АНВЕРС КОНСУЛТ ЕООД | B94: Проблемен | C94: АКТИВНА | D94: NULA | E94: ПЕТЯ ПАВЛОВА | F94: РАДКА НИКОЛОВА | H94: 600 | I94: АТАНАСКА ГОСПОДИНОВА | J94: ДУК+
A95: ЛЮБА ФЕШЪН ЕООД | B95: Ок | C95: БЕЗ ДДС | D95: NULA | E95: АНУШКА РАДЕВА | F95: КРАСИМИРА ГЕОРГИЕВА | H95: 0 | I95: АТАНАСКА ГОСПОДИНОВА | J95: СОЛ+
A96: ДЖИВИЕМСИ МЕНПАУЪР МЕНИДЖМЪНТ ООД | B96: Проблемен | C96: АКТИВНА | D96: NULA | E96: ДИМИТРИНА КОЛЕВА | F96: ВИОЛИНА МИТАКСОВА | H96: 300 | I96: АТАНАСКА ГОСПОДИНОВА | J96: ДУК
A97: ДИГИ 84 ООД | B97: Проблемен | C97: АКТИВНА | D97: 469 | F97: ВИОЛИНА МИТАКСОВА | H97: 1100 | I97: АТАНАСКА ГОСПОДИНОВА | J97: ДУК+
A98: ДИЕНДИ - ФАРМ ЕООД | B98: Проблемен | C98: НУЛЕВО | E98: АНУШКА РАДЕВА | F98: КРАСИМИРА ГЕОРГИЕВА | H98: 0
A99: Д-Р ПЕНКА АТАНАСОВА | B99: Изискващ | C99: АКТИВНА | D99: NULA | E99: ДИМИТРИНА КОЛЕВА | F99: КРАСИМИРА ГЕОРГИЕВА | H99: 0
A100: ЙОШИ ЕООД | B100: Проблемен | C100: БЕЗ ДДС | D100: NULA | E100: АНУШКА РАДЕВА | F100: КРАСИМИРА ГЕОРГИЕВА | H100: 100 | I100: АТАНАСКА ГОСПОДИНОВА | J100: СОЛ+
...

Sheet PayRoll
A1: Име, презиме, фамилия | B1: Нето | C1: Осиг. доход | D1: Осигуровки работодател | E1: Чисто по банка | F1: КЕШ | G1: Тотал | H1: Пълен Разход | I1: 0.1892 | J1: =COUNTA(A2:A21) -> 15
A2: АНГЕЛ ТОДОРОВ | B2: 1000 | C2: 1000 | D2: =C2*$I$1 -> 189.2 | E2: 776 | F2: =B2-E2 -> 224 | G2: =C2+D2 -> 1189.2 | H2: =G2+F2 -> 1413.2
A3: АНЕЛИЯ ПЕНКОВА | B3: 1000 | C3: 1000 | D3: =C3*$I$1 -> 189.2 | E3: 776 | F3: =B3-E3 -> 224 | G3: =C3+D3 -> 1189.2 | H3: =G3+F3 -> 1413.2
A4: АНЕЛИЯ ЩЕРЕВА | B4: 800 | C4: 700 | D4: =C4*$I$1 -> 132.44 | E4: 544 | F4: =B4-E4 -> 256 | G4: =C4+D4 -> 832.44
A5: АТАНАСКА ГОСПОДИНОВА | B5: 1200 | C5: 1000 | D5: =C5*$I$1 -> 189.2 | E5: 776 | F5: =B5-E5 -> 424 | G5: =C5+D5 -> 1189.2 | H5: =G5+F5 -> 1613.2
A6: АНУШКА РАДЕВА | B6: 1200 | C6: 0 | D6: =C6*$I$1 -> 0 | E6: 0 | F6: =B6-E6 -> 1200 | G6: =C6+D6 -> 0 | H6: 1200
A7: ВИОЛИНА МИТАКСОВА | B7: 1280 | C7: 1000 | D7: =C7*$I$1 -> 189.2 | E7: 776 | F7: =B7-E7 -> 504 | G7: =C7+D7 -> 1189.2 | H7: =G7+F7 -> 1693.2
A8: ГАЛИНА ГЕОРГИЕВА | B8: 950 | C8: 1000 | D8: =C8*$I$1 -> 189.2 | E8: 776 | F8: =B8-E8 -> 174 | G8: =C8+D8 -> 1189.2 | H8: =G8+F8 -> 1363.2
A9: ДИМИТРИНА КОЛЕВА | B9: 1175 | C9: 1000 | D9: =C9*$I$1 -> 189.2 | E9: 776 | F9: =B9-E9 -> 399 | G9: =C9+D9 -> 1189.2 | H9: =G9+F9 -> 1588.2
A10: КРАСИМИРА ГЕОРГИЕВА | B10: 1280 | C10: 1000 | D10: =C10*$I$1 -> 189.2 | E10: 776 | F10: =B10-E10 -> 504 | G10: =C10+D10 -> 1189.2 | H10: =G10+F10 -> 1693.2
A11: МАРИЯ МОНЧЕВСКА | B11: 1250 | C11: 1000 | D11: =C11*$I$1 -> 189.2 | E11: 776 | F11: =B11-E11 -> 474 | G11: =C11+D11 -> 1189.2 | H11: =G11+F11 -> 1663.2
A12: МАЯ МАТАНСКА | B12: 1200 | C12: 0 | D12: =C12*$I$1 -> 0 | E12: 0 | F12: =B12-E12 -> 1200 | G12: =C12+D12 -> 0 | H12: =G12+F12 -> 1200
A13: ПЕТЯ ПАВЛОВА | B13: 1050 | C13: 1000 | D13: =C13*$I$1 -> 189.2 | E13: 776 | F13: =B13-E13 -> 274 | G13: =C13+D13 -> 1189.2 | H13: =G13+F13 -> 1463.2
A14: РАДКА НИКОЛОВА | B14: 1533.88 | C14: 1976.7 | D14: =C14*$I$1 -> 373.99164 | E14: 1533.88 | F14: =B14-E14 -> 0 | G14: =C14+D14 -> 2350.6916 | H14: =G14+F14 -> 2350.6916
A15: СИЛВИЯ СТОЯНЧЕВА | B15: 1100 | C15: 1000 | D15: =C15*$I$1 -> 189.2 | E15: 776 | F15: =B15-E15 -> 324 | G15: =C15+D15 -> 1189.2 | H15: =G15+F15 -> 1513.2
A16: СИЛВИЯ ИВАНОВА | B16: 1050 | C16: 1000 | D16: =C16*$I$1 -> 189.2 | E16: 776 | F16: =B16-E16 -> 274 | G16: =C16+D16 -> 1189.2 | H16: =G16+F16 -> 1463.2
F17: =SUBTOTAL(109,Table3[КЕШ]) -> 6455 | H17: =SUBTOTAL(109,Table3[Пълен Разход]) -> 21630.892

Sheet External Expenses
A1: Име, презиме, фамилия | B1: Нето | C1: Осиг. доход | D1: Осигуровки работодател | E1: Чисто по банка | F1: КЕШ | G1: Тотал | H1: Пълен Разход | J1: 0.1892
A2: ЛАСАРА МОРЕНО | B2: 482 | C2: 620.2 | D2: =Table4[[#This Row],[Осиг. доход ]]*$J$1 -> 117.34184 | E2: 482 | G2: =C2+D2 -> 737.54184 | H2: =G2+F2 -> 737.54184 | J2: =COUNTA(A2:A21) -> 6
A3: ДЕЙЛИС РОМЕРО ЕЧАВАРИЯ | B3: =B2 -> 482 | C3: =C2 -> 620.2 | D3: =D2 -> 117.34184 | E3: =E2 -> 482 | F3: =F2 -> 0 | G3: =G2 -> 737.54184 | H3: 0 | J3: 230
A4: НИКОЛ ДАНАИЛОВА ДИЕВА | B4: 482 | C4: 620.2 | D4: =Table4[[#This Row],[Осиг. доход ]]*$J$1 -> 117.34184 | E4: 482 | F4: 0 | G4: =C4+D4 -> 737.54184 | H4: =G4+F4 -> 737.54184
A5: РОСИЦА ДИЕВА САРЕЛСКА | B5: 2500 | C5: 1041 | D5: =Table4[[#This Row],[Осиг. доход ]]*$J$1 -> 196.9572 | E5: 808 | F5: 0 | G5: =C5+D5 -> 1237.9572 | H5: =G5+F5 -> 1237.9572
A6: САБИНА ПЕХЛИВАНОВА ДИЕВА | B6: 2500 | D6: =Table4[[#This Row],[Нето]]*10% -> 250 | E6: 2500 | G6: =C6+D6 -> 250 | H6: =G6+E6 -> 2750
A7: КАЛИН ДИЕВ | B7: 5000 | C7: 2111.64 | D7: =Table4[[#This Row],[Осиг. доход ]]*$J$1 -> 399.52229 | E7: 5000 | G7: 1250 | H7: =G7+E7 -> 6250
H8: =SUBTOTAL(109,Table4[Пълен Разход]) -> 11713.041

Sheet Segment Costs
A1: Име | B1: Отдел | C1: Сума
A2: АНГЕЛ САШЕВ ТОДОРОВ | B2: Acc | C2: 1413.2
A3: АНЕЛИЯ ТОДОРОВА ПЕНКОВА | B3: Admin | C3: 1413.2
A4: АНЕЛИЯ ТОДОРОВА ЩЕРЕВА | B4: Acc | C4: 1088.44
A5: АТАНАСКА КОЛЕВА ГОСПОДИНОВА | B5: HR | C5: 1613.2
A6: ВИОЛИНА ПЛАМЕНОВА МИТАКСОВА | B6: Acc | C6: 1693.2
A7: ГАЛИНА БОРИСЛАВОВА ГЕОРГИЕВА | B7: Acc | C7: 1363.2
A8: ДИМИТРИНА ВИТКОВА КОЛЕВА | B8: Acc | C8: 1588.2
A9: КРАСИМИРА БОРИСЛАВОВА ГЕОРГИЕВА | B9: Acc | C9: 1693.2
A10: МАРИЯ ИЛИЕВА МОНЧЕВСКА | B10: HR | C10: 1663.2
A11: МАЯ МАТАНСКА | B11: Acc | C11: 1200
A12: ПЕТЯ ГЕОРГИЕВА ПАВЛОВА | B12: Acc | C12: 1463.2
A13: РАДКА ИВАНОВА НИКОЛОВА | B13: Acc | C13: 2350.6916
... A15: СИЛВИЯ СТОЯНЧЕВА | B15: Acc | C15: 1513.2
C16: 21519.332
A21: Acc | B21: =SUMIF(Table1[Отдел],"Acc",Table1[Сума]) -> 15366.532
A22: HR | B22: =SUMIF(Table1[Отдел],"HR",Table1[Сума]) -> 4739.6
A23: Admin | B23: =SUMIF(Table1[Отдел],"Admin",Table1[Сума]) -> 1413.2

Sheet Cashfllow
A2: Income | B2: =Master!H188 -> 46520
A3: Cash | B3: 3000
A5: Payroll | B5: =Table3[[#Totals],[Пълен Разход]] -> 21630.892
A6: External | B6: =Table4[[#Totals],[Пълен Разход]] -> 11713.041
A7: Food | B7: =(PayRoll!J1+'External Expenses'!J2)*102 -> 2142
A8: Rents/Property Hub | B8: 6000
A10: Operational | B10: =SUM(B11:B16) -> 2450
A11: Интернет | B11: 100
A12: Слак | B12: 300
A13: Майкрософт | B13: 500
A14: Мобилни | B14: 1000
A15: СОТ | B15: 50
A16: Материали | B16: 500
A19: Total Expenses | B19: =B5+B6+B7+B8+B10 -> 43935.933
A22: TOTAL | B22: =(B2+B3)-B19 -> 5584.0675

Sheet Lists
D3: Колеги | E3: ТРЗ | G3: Статус
D4: АНЕЛИЯ ЩЕРЕВА | E4: АТАНАСКА ГОСПОДИНОВА | G4: АКТИВНА
D5: АНУШКА РАДЕВА | E5: СИЛВИЯ ИВАНОВА | G5: без ДДС
D6: ВИОЛИНА МИТАКСОВА | E6: МАРИЯ МОНЧЕВСКА | G6: НЕ АКТИВНА
D7: ГАЛИНА ГЕОРГИЕВА
D8: ДИМИТРИНА КОЛЕВА
D9: КРАСИМИРА ГЕОРГИЕВА
D10: АНГЕЛ ТОДОРОВ
D11: МАЯ МАТАНСКА
D12: СИЛВИЯ СТОЯНЧЕВА
D13: ПЕТЯ ПАВЛОВА
D14: РАДКА НИКОЛОВА
